LICENSE
MANIFEST.in
README.rst
setup.py
django_postleware.egg-info/PKG-INFO
django_postleware.egg-info/SOURCES.txt
django_postleware.egg-info/dependency_links.txt
django_postleware.egg-info/not-zip-safe
django_postleware.egg-info/requires.txt
django_postleware.egg-info/top_level.txt
postleware/__init__.py
postleware/models.py
postleware/tests.py
postleware/urls.py
postleware/views.py
sample/__init__.py
sample/settings.py
sample/urls.py
sample/wsgi.py