Metadata-Version: 1.0
Name: django-postleware
Version: 1.0.1
Summary: A simple django middleware that ensures POSTs aren't cached by clients.
Home-page: http://github.com/thurloat/django-postleware
Author: Adam Thurlow
Author-email: thurloat@gmail.com
License: BSD
Platform: UNKNOWN
Classifier: Intended Audience :: Developers
Classifier: Intended Audience :: System Administrators
Classifier: Operating System :: OS Independent
Classifier: License :: OSI Approved :: BSD License
Classifier: Programming Language :: Python
Classifier: Framework :: Django
Classifier: Topic :: Software Development
